learningcrux_dl/__init__.py
learningcrux_dl/cli.py
learningcrux_dl/course.py
learningcrux_dl/downloader.py
learningcrux_dl-1.0.2.dist-info/LICENSE
learningcrux_dl-1.0.2.dist-info/METADATA
learningcrux_dl-1.0.2.dist-info/WHEEL
learningcrux_dl-1.0.2.dist-info/entry_points.txt
learningcrux_dl-1.0.2.dist-info/top_level.txt
learningcrux_dl-1.0.2.dist-info/RECORD
