Metadata-Version: 2.1
Name: learningcrux-dl
Version: 1.0.2
Summary: Downloader for learningcrux.com
Home-page: https://github.com/SwapnilSoni1999/learningcrux-dl
Author: Swapnil Soni
Author-email: swapnil.soni12345@gmail.com
License: Unlicensed
Download-URL: https://github.com/SwapnilSoni1999/learningcrux-dl/archive/v0.0.1.tar.gz
Keywords: learningcrux,downloader,learningcrux-dl,lcx-dl
Platform: UNKNOWN
Classifier: Natural Language :: English
Classifier: Programming Language :: Python :: 3 :: Only
Classifier: License :: Public Domain
Classifier: Operating System :: OS Independent
Requires-Python: >=3.6
Requires-Dist: youtube-dl
Requires-Dist: requests
Requires-Dist: lxml
Requires-Dist: bs4
Requires-Dist: click
